## 1
LOAD_FAST 0 (x) - помещаем в стек содержимое локальной переменной x  
LOAD_CONST 1 (10) - помещаем в стек константу 10  
BINARY_MULTIPLY - умножааем 2 элемента стека (10 * х), удаляя их из стека, результат сохраняется в вершине стека  
LOAD_CONST 2 (42) - помещаем в стек константу 42  
BINARY_ADD - сладываем 2 элемента стека (10 * х и 42 соответственно), результат сохраняется в вершине стека  
RETURN_VALUE - возвращаем элемент из вершины стека  

```python
return 10 * x + 42
```

## 2
0 LOAD_CONST 1 (1) - помещаем в стек константу 1  
2 STORE_FAST 1 (r) - сохраняем верхний элемент стека в переменную r ( r = 1 )
4 LOAD_FAST  0 (n) - помещаем в стек содержимое переменной n  
6 LOAD_CONST 1 (1) - помещаем в стек константу 1  
8 COMPARE_OP 4 (>) - сравниваем два верхних элемента стека ( n > 1 )
10 POP_JUMP_IF_FALSE 30 - если ( n > 1 ) ложно - переходим на строку 30 байт-кода
12 LOAD_FAST  1 (r) - помещаем в стек значение перменной r  
14 LOAD_FAST  0 (n) - помещаем в стек значение переменной n  
16 INPLACE_MULTIPLY - переменожаем два верхних элемента стека (r * n)  
18 STORE_FAST 1 (r) - результат сохраняем в переменную r ( r = r*n )  
20 LOAD_FAST  0 (n) - помещаем в стек значение переменной n  
22 LOAD_CONST 1 (1) - помещаем в стек константу 1  
24 INPLACE_SUBTRACT - разность верхних элементов стека ( n-1 )
26 STORE_FAST 0 (n) - результат сохраняем в переменную n ( n = n-1 )
28 JUMP_ABSOLUTE 4  - перейти на 4 строку байт-кода
30 LOAD_FAST  1 (r) - помещаем в стек значение перменной r  
32 RETURN_VALUE     - возвращаем элемент из вершины стека  
> получаем функцию нахождения факториала
```python
def foo(n):
    r = 1
    while n > 1:
        r *= n
        n -= 1
    return r
```
